<?xml version="1.0" encoding="utf-8"?>
<publishData>
  <publishProfile publishUrl="C:\inetpub\wwwroot" deleteExistingFiles="False" ftpAnonymousLogin="False" ftpPassiveMode="True" msdeploySite="" msdeploySiteID="" msdeployRemoteSitePhysicalPath="" msdeployAllowUntrustedCertificate="False" msdeploySkipExtraFilesOnServer="True" msdeployMarkAsApp="False" profileName="ViniSandbox" publishMethod="FileSystem" replaceMatchingFiles="True" userName="" savePWD="False" userPWD="" SelectedForPublish="True">
    <file relUrl="fancybox/source/jquery.fancybox.pack.js" publishTime="11/01/2013 05:16:31" />
    <file relUrl="Views/User/Details.cshtml" publishTime="10/31/2013 12:01:05" />
    <file relUrl="Views/Shared/_FormResources.cshtml" publishTime="10/31/2013 13:35:26" />
    <file relUrl="Scripts/jquery-1.7.1.js" publishTime="10/26/2013 00:20:10" />
    <file relUrl="Content/themes/base/minified/jquery.ui.slider.min.css" publishTime="10/26/2013 00:20:13" />
    <file relUrl="bin/Antlr3.Runtime.dll" publishTime="11/01/2013 16:20:56" />
    <file relUrl="bin/System.Web.WebPages.dll" publishTime="11/01/2013 16:20:48" />
    <file relUrl="Views/File/Create.cshtml" publishTime="10/30/2013 09:47:09" />
    <file relUrl="fancybox/lib/jquery.mousewheel-3.0.6.pack.js" publishTime="11/01/2013 05:16:31" />
    <file relUrl="bin/DotNetOpenAuth.AspNet.xml" publishTime="11/01/2013 16:19:47" />
    <file relUrl="Scripts/jquery.validate.unobtrusive.js" publishTime="10/26/2013 00:20:15" />
    <file relUrl="Content/themes/base/jquery.ui.datepicker.css" publishTime="10/26/2013 00:20:14" />
    <file relUrl="bin/System.Web.Helpers.xml" publishTime="11/01/2013 16:20:48" />
    <file relUrl="Views/File/Index.cshtml" publishTime="10/31/2013 17:36:40" />
    <file relUrl="bin/DotNetOpenAuth.OpenId.RelyingParty.xml" publishTime="11/01/2013 16:19:47" />
    <file relUrl="bin/WebMatrix.WebData.xml" publishTime="11/01/2013 16:20:48" />
    <file relUrl="Content/themes/base/minified/jquery-ui.min.css" publishTime="10/26/2013 00:20:13" />
    <file relUrl="Content/themes/base/images/ui-bg_glass_95_fef1ec_1x400.png" publishTime="10/26/2013 00:20:14" />
    <file relUrl="Scripts/jquery.form.js" publishTime="10/28/2013 13:43:15" />
    <file relUrl="Content/themes/base/minified/jquery.ui.autocomplete.min.css" publishTime="10/26/2013 00:20:14" />
    <file relUrl="bin/Microsoft.Web.Infrastructure.dll" publishTime="11/01/2013 16:20:48" />
    <file relUrl="bin/ViniSandboxDAL.pdb" publishTime="11/05/2013 01:29:55" />
    <file relUrl="Content/themes/base/images/ui-bg_highlight-soft_75_cccccc_1x100.png" publishTime="10/26/2013 00:20:14" />
    <file relUrl="Views/File/Reanalize.cshtml" publishTime="10/31/2013 12:15:00" />
    <file relUrl="Scripts/_references.js" publishTime="10/26/2013 00:19:51" />
    <file relUrl="Content/themes/base/jquery.ui.selectable.css" publishTime="10/26/2013 00:20:14" />
    <file relUrl="Content/themes/base/minified/images/ui-icons_222222_256x240.png" publishTime="10/26/2013 00:20:14" />
    <file relUrl="Views/Analysis/_Dynamic.cshtml" publishTime="11/01/2013 05:10:33" />
    <file relUrl="Scripts/jquery.validate.js" publishTime="10/26/2013 00:20:11" />
    <file relUrl="Views/Analysis/_DnsGrid.cshtml" publishTime="11/01/2013 04:02:04" />
    <file relUrl="bin/DotNetOpenAuth.OpenId.RelyingParty.dll" publishTime="11/01/2013 16:19:47" />
    <file relUrl="Views/Analysis/_Static.cshtml" publishTime="11/01/2013 02:46:45" />
    <file relUrl="bin/System.Web.Razor.xml" publishTime="11/01/2013 16:20:38" />
    <file relUrl="bin/System.Net.Http.xml" publishTime="10/26/2013 00:20:22" />
    <file relUrl="bin/DotNetOpenAuth.Core.dll" publishTime="10/26/2013 00:20:27" />
    <file relUrl="Content/themes/base/jquery.ui.all.css" publishTime="10/26/2013 00:20:14" />
    <file relUrl="Content/ico/malicious_disable.png" publishTime="11/01/2013 15:15:04" />
    <file relUrl="fancybox/source/fancybox_loading@2x.gif" publishTime="11/01/2013 05:16:31" />
    <file relUrl="Views/Home/Index.cshtml" publishTime="11/01/2013 15:34:27" />
    <file relUrl="bin/System.Net.Http.Formatting.xml" publishTime="11/01/2013 16:20:38" />
    <file relUrl="Scripts/jquery.validate.unobtrusive.min.js" publishTime="10/26/2013 00:20:15" />
    <file relUrl="Views/Shared/Awesome/Lookup.ascx" publishTime="10/28/2013 13:43:14" />
    <file relUrl="Views/Shared/Awesome/Autocomplete.ascx" publishTime="10/28/2013 13:43:14" />
    <file relUrl="bin/ViniSandboxPoco.dll" publishTime="11/05/2013 01:29:55" />
    <file relUrl="Views/Shared/_Searcher.cshtml" publishTime="10/28/2013 22:06:57" />
    <file relUrl="Views/Shared/Error.cshtml" publishTime="10/26/2013 00:19:51" />
    <file relUrl="Content/themes/base/minified/jquery.ui.progressbar.min.css" publishTime="10/26/2013 00:20:13" />
    <file relUrl="Scripts/Awesome.min.js" publishTime="10/28/2013 13:43:15" />
    <file relUrl="Scripts/jquery-1.7.1.min.js" publishTime="10/26/2013 00:20:09" />
    <file relUrl="bin/Omu.Awesome.Core.dll" publishTime="11/01/2013 16:20:56" />
    <file relUrl="bin/Omu.Awesome.Mvc.dll" publishTime="11/01/2013 16:20:56" />
    <file relUrl="bin/Newtonsoft.Json.xml" publishTime="11/01/2013 16:20:38" />
    <file relUrl="Content/ico/redo.png" publishTime="11/01/2013 15:15:06" />
    <file relUrl="Content/ico/delete.png" publishTime="10/29/2013 00:25:20" />
    <file relUrl="Images/orderedList4.png" publishTime="10/26/2013 00:19:51" />
    <file relUrl="Views/Analysis/_SectionGrid.cshtml" publishTime="10/31/2013 22:37:17" />
    <file relUrl="bin/System.Web.Helpers.dll" publishTime="11/01/2013 16:20:48" />
    <file relUrl="Content/themes/base/images/ui-bg_glass_55_fbf9ee_1x400.png" publishTime="10/26/2013 00:20:14" />
    <file relUrl="bin/MySql.Data.Entity.dll" publishTime="06/13/2013 02:24:56" />
    <file relUrl="Views/Shared/Awesome/AjaxCheckBoxList.ascx" publishTime="10/28/2013 13:43:15" />
    <file relUrl="bin/Ionic.Zip.dll" publishTime="11/01/2013 16:19:47" />
    <file relUrl="Content/themes/base/minified/jquery.ui.accordion.min.css" publishTime="10/26/2013 00:20:14" />
    <file relUrl="Content/themes/base/jquery-ui.css" publishTime="10/26/2013 00:20:14" />
    <file relUrl="Content/themes/base/minified/jquery.ui.resizable.min.css" publishTime="10/26/2013 00:20:13" />
    <file relUrl="Content/themes/base/jquery.ui.resizable.css" publishTime="10/26/2013 00:20:14" />
    <file relUrl="bin/System.Net.Http.Formatting.dll" publishTime="11/01/2013 16:20:38" />
    <file relUrl="Content/themes/base/jquery.ui.tabs.css" publishTime="10/26/2013 00:20:14" />
    <file relUrl="bin/System.Web.WebPages.xml" publishTime="11/01/2013 16:20:48" />
    <file relUrl="Scripts/knockout-2.1.0.debug.js" publishTime="10/26/2013 00:20:31" />
    <file relUrl="fancybox/source/jquery.fancybox.js" publishTime="11/01/2013 05:16:31" />
    <file relUrl="fancybox/source/fancybox_sprite@2x.png" publishTime="11/01/2013 05:16:31" />
    <file relUrl="Images/orderedList1.png" publishTime="10/26/2013 00:19:51" />
    <file relUrl="Content/themes/base/images/ui-icons_2e83ff_256x240.png" publishTime="10/26/2013 00:20:14" />
    <file relUrl="Content/themes/base/minified/jquery.ui.tabs.min.css" publishTime="10/26/2013 00:20:13" />
    <file relUrl="Views/Shared/Awesome/MultiLookupPopup.ascx" publishTime="10/28/2013 13:43:14" />
    <file relUrl="bin/System.Web.WebPages.Deployment.dll" publishTime="11/01/2013 16:20:48" />
    <file relUrl="bin/DotNetOpenAuth.Core.xml" publishTime="10/26/2013 00:20:27" />
    <file relUrl="Views/Account/Login.cshtml" publishTime="11/01/2013 15:43:21" />
    <file relUrl="Scripts/jquery-ui-1.8.20.min.js" publishTime="10/26/2013 00:20:13" />
    <file relUrl="Views/File/_GridFile.cshtml" publishTime="10/30/2013 23:57:03" />
    <file relUrl="Images/heroAccent.png" publishTime="10/26/2013 00:19:51" />
    <file relUrl="Views/Analysis/_ResourceGrid.cshtml" publishTime="10/31/2013 22:36:45" />
    <file relUrl="Content/themes/base/jquery.ui.accordion.css" publishTime="10/26/2013 00:20:14" />
    <file relUrl="Global.asax" publishTime="10/26/2013 00:19:51" />
    <file relUrl="Images/orderedList3.png" publishTime="10/26/2013 00:19:51" />
    <file relUrl="Images/orderedList5.png" publishTime="10/26/2013 00:19:51" />
    <file relUrl="Content/themes/base/minified/jquery.ui.theme.min.css" publishTime="10/26/2013 00:20:13" />
    <file relUrl="Web.config" publishTime="11/05/2013 01:30:07" />
    <file relUrl="packages.config" publishTime="10/30/2013 12:54:36" />
    <file relUrl="Images/orderedList8.png" publishTime="10/26/2013 00:19:51" />
    <file relUrl="Scripts/Awesome.js" publishTime="10/28/2013 13:43:15" />
    <file relUrl="Content/themes/base/minified/images/ui-bg_glass_65_ffffff_1x400.png" publishTime="10/26/2013 00:20:14" />
    <file relUrl="Views/Shared/Awesome/AjaxRadioList.ascx" publishTime="10/28/2013 13:43:14" />
    <file relUrl="bin/System.Web.Mvc.xml" publishTime="11/01/2013 16:20:38" />
    <file relUrl="Views/Analysis/Index.cshtml" publishTime="10/31/2013 17:47:21" />
    <file relUrl="fancybox/source/helpers/jquery.fancybox-thumbs.css" publishTime="11/01/2013 05:16:31" />
    <file relUrl="Content/themes/base/jquery.ui.dialog.css" publishTime="10/26/2013 00:20:14" />
    <file relUrl="Scripts/jquery.mvccontrib.grid.js" publishTime="10/31/2013 17:55:06" />
    <file relUrl="Views/Analysis/Edit.cshtml" publishTime="10/31/2013 13:41:48" />
    <file relUrl="Content/themes/base/minified/images/ui-icons_2e83ff_256x240.png" publishTime="10/26/2013 00:20:14" />
    <file relUrl="bin/Microsoft.Web.WebPages.OAuth.dll" publishTime="11/01/2013 16:20:48" />
    <file relUrl="bin/WebMatrix.Data.dll" publishTime="11/01/2013 16:20:48" />
    <file relUrl="fancybox/source/helpers/fancybox_buttons.png" publishTime="11/01/2013 05:16:31" />
    <file relUrl="Content/themes/base/minified/images/ui-bg_glass_55_fbf9ee_1x400.png" publishTime="10/26/2013 00:20:14" />
    <file relUrl="Content/themes/base/images/ui-icons_222222_256x240.png" publishTime="10/26/2013 00:20:14" />
    <file relUrl="Views/Shared/Awesome/Popup.ascx" publishTime="10/28/2013 13:43:14" />
    <file relUrl="Content/themes/base/minified/images/ui-icons_cd0a0a_256x240.png" publishTime="10/26/2013 00:20:14" />
    <file relUrl="Views/Shared/Awesome/SearchForm.ascx" publishTime="10/28/2013 13:43:14" />
    <file relUrl="Views/Shared/Awesome/Confirm.ascx" publishTime="10/28/2013 13:43:14" />
    <file relUrl="bin/DotNetOpenAuth.OpenId.xml" publishTime="11/01/2013 16:19:47" />
    <file relUrl="bin/System.Web.Optimization.dll" publishTime="11/01/2013 16:20:48" />
    <file relUrl="Content/themes/base/minified/jquery.ui.dialog.min.css" publishTime="10/26/2013 00:20:13" />
    <file relUrl="bin/EntityFramework.xml" publishTime="10/26/2013 00:19:58" />
    <file relUrl="bin/DotNetOpenAuth.OAuth.xml" publishTime="11/01/2013 16:19:47" />
    <file relUrl="Content/themes/base/minified/images/ui-bg_glass_75_e6e6e6_1x400.png" publishTime="10/26/2013 00:20:14" />
    <file relUrl="Views/_ViewStart.cshtml" publishTime="10/28/2013 15:32:30" />
    <file relUrl="Content/themes/base/jquery.ui.autocomplete.css" publishTime="10/26/2013 00:20:14" />
    <file relUrl="fancybox/source/fancybox_sprite.png" publishTime="11/01/2013 05:16:31" />
    <file relUrl="fancybox/source/helpers/jquery.fancybox-thumbs.js" publishTime="11/01/2013 05:16:31" />
    <file relUrl="Images/orderedList9.png" publishTime="10/26/2013 00:19:51" />
    <file relUrl="Views/File/Details.cshtml" publishTime="10/31/2013 12:45:38" />
    <file relUrl="bin/EntityFramework.dll" publishTime="10/26/2013 17:53:31" />
    <file relUrl="! mvc project awesome readme.txt" publishTime="10/28/2013 13:43:15" />
    <file relUrl="Content/themes/base/images/ui-bg_glass_75_e6e6e6_1x400.png" publishTime="10/26/2013 00:20:14" />
    <file relUrl="favicon.ico" publishTime="10/29/2013 01:00:56" />
    <file relUrl="Images/accent.png" publishTime="10/26/2013 00:19:51" />
    <file relUrl="Scripts/jquery.validate-vsdoc.js" publishTime="10/26/2013 00:20:11" />
    <file relUrl="Content/themes/base/jquery.ui.theme.css" publishTime="10/26/2013 00:20:14" />
    <file relUrl="Content/themes/base/minified/images/ui-icons_454545_256x240.png" publishTime="10/26/2013 00:20:14" />
    <file relUrl="Scripts/jquery.unobtrusive-ajax.js" publishTime="10/26/2013 00:20:16" />
    <file relUrl="Content/themes/base/minified/images/ui-bg_glass_75_dadada_1x400.png" publishTime="10/26/2013 00:20:14" />
    <file relUrl="Content/themes/base/minified/images/ui-bg_flat_75_ffffff_40x100.png" publishTime="10/26/2013 00:20:14" />
    <file relUrl="Views/Analysis/_ImportsGrid.cshtml" publishTime="10/31/2013 20:29:41" />
    <file relUrl="Images/orderedList7.png" publishTime="10/26/2013 00:19:51" />
    <file relUrl="Content/themes/base/minified/jquery.ui.button.min.css" publishTime="10/26/2013 00:20:14" />
    <file relUrl="bin/WebActivator.pdb" publishTime="11/01/2013 16:20:56" />
    <file relUrl="Scripts/jquery-1.7.1-vsdoc.js" publishTime="10/26/2013 00:20:09" />
    <file relUrl="bin/System.Net.Http.WebRequest.xml" publishTime="10/26/2013 00:20:22" />
    <file relUrl="bin/DotNetOpenAuth.AspNet.dll" publishTime="11/01/2013 16:19:47" />
    <file relUrl="Content/themes/base/images/ui-bg_glass_75_dadada_1x400.png" publishTime="10/26/2013 00:20:14" />
    <file relUrl="Scripts/jquery.mvccontrib.grid.min.js" publishTime="10/28/2013 23:27:05" />
    <file relUrl="Content/themes/base/jquery.ui.button.css" publishTime="10/26/2013 00:20:14" />
    <file relUrl="Views/File/Malicious.cshtml" publishTime="10/31/2013 12:14:51" />
    <file relUrl="Content/themes/base/minified/images/ui-icons_888888_256x240.png" publishTime="10/26/2013 00:20:14" />
    <file relUrl="bin/WebViniSandbox.pdb" publishTime="11/05/2013 01:29:56" />
    <file relUrl="bin/MvcContrib.dll" publishTime="03/22/2011 13:47:02" />
    <file relUrl="Content/themes/base/jquery.ui.core.css" publishTime="10/26/2013 00:20:14" />
    <file relUrl="Scripts/jquery.form.min.js" publishTime="10/28/2013 16:31:17" />
    <file relUrl="Content/themes/base/images/ui-bg_glass_65_ffffff_1x400.png" publishTime="10/26/2013 00:20:14" />
    <file relUrl="bin/System.Web.WebPages.Razor.xml" publishTime="11/01/2013 16:20:48" />
    <file relUrl="Views/Analysis/_ExportsGrid.cshtml" publishTime="10/31/2013 22:19:44" />
    <file relUrl="bin/System.Web.Mvc.dll" publishTime="11/01/2013 16:20:38" />
    <file relUrl="Views/Shared/_GridResources.cshtml" publishTime="10/30/2013 17:46:22" />
    <file relUrl="Views/Shared/Awesome/AjaxDropdown.ascx" publishTime="10/28/2013 13:43:14" />
    <file relUrl="Views/Shared/_Layout.cshtml" publishTime="11/01/2013 15:46:30" />
    <file relUrl="Content/themes/base/minified/images/ui-bg_glass_95_fef1ec_1x400.png" publishTime="10/26/2013 00:20:14" />
    <file relUrl="fancybox/source/fancybox_loading.gif" publishTime="11/01/2013 05:16:31" />
    <file relUrl="bin/DotNetOpenAuth.OAuth.dll" publishTime="11/01/2013 16:19:47" />
    <file relUrl="bin/WebGrease.dll" publishTime="11/01/2013 16:20:56" />
    <file relUrl="Images/orderedList2.png" publishTime="10/26/2013 00:19:51" />
    <file relUrl="Views/Analysis/Details.cshtml" publishTime="11/01/2013 05:32:03" />
    <file relUrl="bin/System.Web.Razor.dll" publishTime="11/01/2013 16:20:38" />
    <file relUrl="bin/WebActivator.dll" publishTime="11/01/2013 16:20:56" />
    <file relUrl="bin/WebMatrix.WebData.dll" publishTime="11/01/2013 16:20:48" />
    <file relUrl="bin/MvcContrib.Shp.dll" publishTime="06/02/2011 19:55:15" />
    <file relUrl="Views/Shared/Awesome/LookupPopup.ascx" publishTime="10/28/2013 13:43:14" />
    <file relUrl="bin/System.Web.Http.WebHost.dll" publishTime="11/01/2013 16:20:39" />
    <file relUrl="Content/themes/base/images/ui-bg_flat_0_aaaaaa_40x100.png" publishTime="10/26/2013 00:20:15" />
    <file relUrl="Content/themes/base/images/ui-icons_454545_256x240.png" publishTime="10/26/2013 00:20:14" />
    <file relUrl="Views/Shared/_LoginPartial.cshtml" publishTime="10/29/2013 15:37:31" />
    <file relUrl="Views/Shared/Awesome/MultiLookup.ascx" publishTime="10/28/2013 13:43:14" />
    <file relUrl="Content/themes/base/images/ui-icons_cd0a0a_256x240.png" publishTime="10/26/2013 00:20:14" />
    <file relUrl="bin/System.Net.Http.dll" publishTime="10/26/2013 00:20:21" />
    <file relUrl="Views/Shared/Awesome/header.ascx" publishTime="10/28/2013 13:43:14" />
    <file relUrl="bin/MySql.Data.dll" publishTime="06/13/2013 02:24:56" />
    <file relUrl="Content/themes/base/jquery.ui.slider.css" publishTime="10/26/2013 00:20:14" />
    <file relUrl="bin/DotNetOpenAuth.OpenId.dll" publishTime="11/01/2013 16:19:47" />
    <file relUrl="Content/themes/base/minified/jquery.ui.core.min.css" publishTime="10/26/2013 00:20:14" />
    <file relUrl="bin/ViniSandboxDAL.dll" publishTime="11/05/2013 01:29:55" />
    <file relUrl="Content/images/biohazard.png" publishTime="10/29/2013 01:39:55" />
    <file relUrl="Content/themes/base/images/ui-bg_flat_75_ffffff_40x100.png" publishTime="10/26/2013 00:20:14" />
    <file relUrl="fancybox/lib/jquery-1.10.1.min.js" publishTime="11/01/2013 05:16:31" />
    <file relUrl="Content/Site.css" publishTime="11/01/2013 15:44:11" />
    <file relUrl="bin/Microsoft.Web.WebPages.OAuth.xml" publishTime="11/01/2013 16:20:48" />
    <file relUrl="bin/System.Web.WebPages.Razor.dll" publishTime="11/01/2013 16:20:48" />
    <file relUrl="Content/themes/base/minified/images/ui-bg_flat_0_aaaaaa_40x100.png" publishTime="10/26/2013 00:20:14" />
    <file relUrl="Views/Analysis/_InfoGrid.cshtml" publishTime="11/01/2013 04:41:38" />
    <file relUrl="bin/Ionic.Zip.xml" publishTime="11/01/2013 16:19:48" />
    <file relUrl="fancybox/source/helpers/jquery.fancybox-buttons.js" publishTime="11/01/2013 05:16:31" />
    <file relUrl="fancybox/source/fancybox_overlay.png" publishTime="11/01/2013 05:16:31" />
    <file relUrl="Views/Analysis/_EventsGrid.cshtml" publishTime="11/01/2013 04:01:44" />
    <file relUrl="bin/ViniSandboxPoco.pdb" publishTime="11/05/2013 01:29:55" />
    <file relUrl="Views/Analysis/_Grid.cshtml" publishTime="10/31/2013 16:25:14" />
    <file relUrl="Views/Shared/Awesome/LookupList.ascx" publishTime="10/28/2013 13:43:14" />
    <file relUrl="Content/mvccontrib.grid.css" publishTime="10/28/2013 23:27:33" />
    <file relUrl="bin/System.Web.Http.WebHost.xml" publishTime="11/01/2013 16:20:39" />
    <file relUrl="Views/Analysis/_Images.cshtml" publishTime="11/01/2013 05:11:27" />
    <file relUrl="Scripts/jquery-ui-1.8.20.js" publishTime="10/26/2013 00:20:13" />
    <file relUrl="bin/System.Web.Http.dll" publishTime="11/01/2013 16:20:38" />
    <file relUrl="Scripts/modernizr-2.5.3.js" publishTime="10/26/2013 00:20:16" />
    <file relUrl="Views/Account/_ChangePasswordPartial.cshtml" publishTime="11/02/2013 19:43:11" />
    <file relUrl="bin/System.Web.Http.xml" publishTime="11/01/2013 16:20:38" />
    <file relUrl="Content/themes/base/images/ui-icons_888888_256x240.png" publishTime="10/26/2013 00:20:14" />
    <file relUrl="bin/Newtonsoft.Json.dll" publishTime="11/01/2013 16:20:38" />
    <file relUrl="fancybox/source/blank.gif" publishTime="11/01/2013 05:16:31" />
    <file relUrl="Content/ico/send.png" publishTime="11/01/2013 15:15:07" />
    <file relUrl="Content/themes/base/jquery.ui.progressbar.css" publishTime="10/26/2013 00:20:14" />
    <file relUrl="Images/bullet.png" publishTime="10/26/2013 00:19:51" />
    <file relUrl="Content/themes/base/minified/jquery.ui.selectable.min.css" publishTime="10/26/2013 00:20:13" />
    <file relUrl="fancybox/lib/jquery-1.9.0.min.js" publishTime="11/01/2013 05:16:31" />
    <file relUrl="Content/ico/details.png" publishTime="10/29/2013 00:25:20" />
    <file relUrl="Scripts/knockout-2.1.0.js" publishTime="10/26/2013 00:20:31" />
    <file relUrl="Views/Analysis/_ScanGrid.cshtml" publishTime="11/01/2013 03:59:51" />
    <file relUrl="bin/System.Net.Http.WebRequest.dll" publishTime="10/26/2013 00:20:22" />
    <file relUrl="Images/orderedList6.png" publishTime="10/26/2013 00:19:51" />
    <file relUrl="Views/File/_GridFileDet.cshtml" publishTime="10/31/2013 00:18:13" />
    <file relUrl="fancybox/source/helpers/jquery.fancybox-buttons.css" publishTime="11/01/2013 05:16:31" />
    <file relUrl="bin/DotNetOpenAuth.OAuth.Consumer.xml" publishTime="11/01/2013 16:19:47" />
    <file relUrl="Views/User/_Grid.cshtml" publishTime="10/29/2013 16:24:58" />
    <file relUrl="fancybox/source/jquery.fancybox.css" publishTime="11/01/2013 05:16:31" />
    <file relUrl="Views/Account/Manage.cshtml" publishTime="10/29/2013 15:24:45" />
    <file relUrl="Views/Web.config" publishTime="10/28/2013 23:25:56" />
    <file relUrl="Content/Awesome.css" publishTime="10/28/2013 13:43:15" />
    <file relUrl="Views/User/Edit.cshtml" publishTime="10/31/2013 11:54:18" />
    <file relUrl="Content/ico/malicious.png" publishTime="11/01/2013 15:15:03" />
    <file relUrl="Scripts/jquery.validate.min.js" publishTime="10/26/2013 00:20:11" />
    <file relUrl="Views/Account/Register.cshtml" publishTime="11/02/2013 19:38:34" />
    <file relUrl="bin/DotNetOpenAuth.OAuth.Consumer.dll" publishTime="11/01/2013 16:19:47" />
    <file relUrl="fancybox/source/helpers/jquery.fancybox-media.js" publishTime="11/01/2013 05:16:31" />
    <file relUrl="Views/Shared/Awesome/PopupForm.ascx" publishTime="10/28/2013 13:43:14" />
    <file relUrl="bin/WebMatrix.Data.xml" publishTime="11/01/2013 16:20:48" />
    <file relUrl="bin/WebViniSandbox.dll" publishTime="11/05/2013 01:29:56" />
    <file relUrl="Scripts/jquery.unobtrusive-ajax.min.js" publishTime="10/26/2013 00:20:16" />
    <file relUrl="Views/Analysis/_MiscellaneousGrid.cshtml" publishTime="10/31/2013 23:14:48" />
    <file relUrl="Content/ico/edit.png" publishTime="10/29/2013 00:25:20" />
    <file relUrl="Content/themes/base/minified/jquery.ui.datepicker.min.css" publishTime="10/26/2013 00:20:13" />
    <file relUrl="Views/File/SendAntivirus.cshtml" publishTime="10/31/2013 12:15:09" />
    <file relUrl="Views/User/Index.cshtml" publishTime="10/31/2013 12:02:19" />
    <file relUrl="Images/orderedList0.png" publishTime="10/26/2013 00:19:51" />
    <file relUrl="Content/themes/base/jquery.ui.base.css" publishTime="10/26/2013 00:20:14" />
    <file relUrl="Content/themes/base/minified/images/ui-bg_highlight-soft_75_cccccc_1x100.png" publishTime="10/26/2013 00:20:14" />
    <file relUrl="bin/System.Web.WebPages.Deployment.xml" publishTime="11/01/2013 16:20:48" />
  </publishProfile>
</publishData>